02/ALU-nostat.v
module ALUnostat(
    input [15:0] x, y,
    input zx, nx, zy, ny, f, no,
    output [15:0] out);

    wire [15:0] outzx, outnx, outzy, outny, outno;

    assign  outzx = zx ? (16'h0000) : (x);
    assign  outnx = nx ? (~outzx) : (outzx);

    assign  outzy = zy ? (16'h0000) : (y);
    assign  outny = ny ? (~outzy) : (outzy);

    assign out = f ? (outnx + outny) : (outnx && outny);

    assign outno = no ? (~out) : (out);

endmodule

02/ALU-nostat_tb.v
`default_nettype none
module ALUnostat_tb();
    
    integer file;

    reg [15:0] x, y;
    reg zx, nx, zy, ny, f, no;
    wire [15:0] out;

    reg [53:0] testvectors [35:0];

    ALUnostat dut(
	    .x(x),
	    .y(y),
	    .zx(zx),
	    .nx(nx),
	    .zy(zy),
	    .ny(ny),
	    .f(f),
	    .no(no),
	    .out(out)
    );

    task display;
        #1 $fwrite(file, "| %16b | %16b | %1b | %1b | %1b | %1b | %1b | %1b | %16b |\n", x, y, zx, nx, zy, ny, f, no, out);
    endtask

    initial begin
        $dumpfile("ALU-nostat_tb.vcd");
        $dumpvars(0, ALUnostat_tb);
        file = $fopen("ALU-nostat.out","w");
        $fwrite(file, "|        x         |        y         |zx |nx |zy |ny | f |no |       out        |\n");

        $readmemb("ALU-nostat.tv", testvectors, 0, 35);

        for(integer i = 0; i < 36; i = i + 1) begin
		x = testvectors[i][53:38];
		y = testvectors[i][37:22];
		zx = testvectors[i][21];
		nx = testvectors[i][20];
		zy = testvectors[i][19];
		ny = testvectors[i][18];
		f = testvectors[i][17];
		no = testvectors[i][16];
		display();
        end

        $finish();
    end
endmodule

02/ALU-nostat_tb.vcd
$date
	Sun Nov  3 00:20:16 2024
$end
$version
	Icarus Verilog
$end
$timescale
	1s
$end
$scope module ALUnostat_tb $end
$var wire 16 ! out [15:0] $end
$var reg 1 " f $end
$var reg 1 # no $end
$var reg 1 $ nx $end
$var reg 1 % ny $end
$var reg 16 & x [15:0] $end
$var reg 16 ' y [15:0] $end
$var reg 1 ( zx $end
$var reg 1 ) zy $end
$var integer 32 * file [31:0] $end
$scope module dut $end
$var wire 1 " f $end
$var wire 1 # no $end
$var wire 1 $ nx $end
$var wire 1 % ny $end
$var wire 16 + x [15:0] $end
$var wire 16 , y [15:0] $end
$var wire 1 ( zx $end
$var wire 1 ) zy $end
$var wire 16 - outzy [15:0] $end
$var wire 16 . outzx [15:0] $end
$var wire 16 / outny [15:0] $end
$var wire 16 0 outnx [15:0] $end
$var wire 16 1 outno [15:0] $end
$var wire 16 2 out [15:0] $end
$upscope $end
$scope begin $ivl_for_loop0 $end
$var integer 32 3 i [31:0] $end
$upscope $end
$scope task display $end
$upscope $end
$upscope $end
$enddefinitions $end
$comment Show the parameter values. $end
$dumpall
$end
#0
$dumpvars
b0 3
b0 2
b0 1
b0 0
b0 /
b0 .
b0 -
b1111111111111111 ,
b0 +
b10000000000000000000000000000011 *
1)
1(
b1111111111111111 '
b0 &
0%
0$
0#
1"
b0 !
$end
#1
b1111111111111110 !
b1111111111111110 2
b1 1
b1111111111111111 /
b1111111111111111 0
1#
1%
1$
b1 3
#2
b1111111111111111 !
b1111111111111111 2
b1111111111111111 1
b0 /
0#
0%
b10 3
#3
b0 1
b0 !
b0 2
b1111111111111111 /
b0 0
0"
1%
0$
0(
b11 3
#4
b1 1
b1 !
b1 2
b1111111111111111 -
b1111111111111111 0
0%
0)
1$
1(
b100 3
#5
b0 !
b0 2
b1111111111111111 1
b1111111111111111 /
b0 -
b0 0
1#
1%
1)
0$
0(
b101 3
#6
b1111111111111110 1
b1 !
b1 2
b1111111111111111 -
b1111111111111111 0
0%
0)
1$
1(
b110 3
#7
b0 1
b1111111111111111 !
b1111111111111111 2
b1111111111111111 /
b0 -
b0 0
1"
1%
1)
0$
0(
b111 3
#8
b1 1
b1111111111111110 !
b1111111111111110 2
b1111111111111111 -
b1111111111111111 0
0%
0)
1$
1(
b1000 3
#9
b1 1
b1111111111111110 !
b1111111111111110 2
b1111111111111111 /
b0 -
1%
1)
0(
b1001 3
#10
b0 1
b1111111111111111 !
b1111111111111111 2
b0 /
b1111111111111111 -
0)
1(
b1010 3
#11
b1111111111111111 /
b1111111111111111 !
b1111111111111111 2
b1111111111111111 1
b0 -
b0 0
0#
1)
0$
0(
b1011 3
#12
b1111111111111110 1
b1111111111111110 !
b1111111111111110 2
b1111111111111111 -
b1111111111111111 0
0%
0)
1$
1(
b1100 3
#13
b1111111111111111 1
b1111111111111111 !
b1111111111111111 2
b0 0
0$
0(
b1101 3
#14
b1111111111111110 !
b1111111111111110 2
b1 1
b1111111111111111 0
1#
1$
b1110 3
#15
b1111111111111111 1
b0 !
b0 2
b0 /
b0 0
1%
0$
b1111 3
#16
b0 1
b1111111111111111 /
0#
0"
0%
b10000 3
#17
b1111111111111111 1
b0 /
b1111111111111111 0
1#
1%
1$
b10001 3
#18
b0 1
b0 0
b0 -
0#
1"
0%
1)
0$
1(
b1111011010010 '
b1111011010010 ,
b101101110100000 &
b101101110100000 +
b10010 3
#19
b1111111111111110 !
b1111111111111110 2
b1 1
b1111111111111111 /
b1111111111111111 0
1#
1%
1$
b10011 3
#20
b1111111111111111 !
b1111111111111111 2
b1111111111111111 1
b0 /
0#
0%
b10100 3
#21
b1 1
b1 !
b1 2
b1111111111111111 /
b101101110100000 0
b101101110100000 .
0"
1%
0$
0(
b10101 3
#22
b1111011010010 /
b1111011010010 -
b1111111111111111 0
b0 .
0%
0)
1$
1(
b10110 3
#23
b1111111111111110 1
b1111111111111111 /
b0 -
b101101110100000 0
b101101110100000 .
1#
1%
1)
0$
0(
b10111 3
#24
b1111011010010 /
b1111011010010 -
b1111111111111111 0
b0 .
0%
0)
1$
1(
b11000 3
#25
b1010010001100000 1
b101101110011111 !
b101101110011111 2
b1111111111111111 /
b0 -
b101101110100000 0
b101101110100000 .
1"
1%
1)
0$
0(
b11001 3
#26
b1110000100101110 1
b1111011010001 !
b1111011010001 2
b1111011010010 /
b1111011010010 -
b1111111111111111 0
b0 .
0%
0)
1$
1(
b11010 3
#27
b101101110100001 1
b1010010001011111 0
b1010010001011110 !
b1010010001011110 2
b1111111111111111 /
b0 -
b101101110100000 .
1%
1)
0(
b11011 3
#28
b1111011010011 1
b1110000100101100 !
b1110000100101100 2
b1110000100101101 /
b1111111111111111 0
b1111011010010 -
b0 .
0)
1(
b11100 3
#29
b1111111111111111 /
b101101110011111 !
b101101110011111 2
b101101110011111 1
b0 -
b101101110100000 0
b101101110100000 .
0#
1)
0$
0(
b11101 3
#30
b1111011010001 1
b1111011010001 !
b1111011010001 2
b1111011010010 /
b1111011010010 -
b1111111111111111 0
b0 .
0%
0)
1$
1(
b11110 3
#31
b111101001110010 1
b111101001110010 !
b111101001110010 2
b101101110100000 0
b101101110100000 .
0$
0(
b11111 3
#32
b1100001100110001 !
b1100001100110001 2
b11110011001110 1
b1010010001011111 0
1#
1$
b100000 3
#33
b1100001100110010 1
b11110011001101 !
b11110011001101 2
b1110000100101101 /
b101101110100000 0
1%
0$
b100001 3
#34
b1 1
b1 !
b1 2
b1111011010010 /
0#
0"
0%
b100010 3
#35
b1111111111111110 1
b1110000100101101 /
b1010010001011111 0
1#
1%
1$
b100011 3
#36
b100100 3
