02/ALU.v
module ALU(
    input [15:0] x, y,
    input zx, nx, zy, ny, f, no,
    output [15:0] out,
    output zr, ng);

    wire [15:0] outzx, outnx, outzy, outny, outno;

    assign  outzx = zx ? (16'h0000) : (x);
    assign  outnx = nx ? (~outzx) : (outzx);

    assign  outzy = zy ? (16'h0000) : (y);
    assign  outny = ny ? (~outzy) : (outzy);

    assign out = f ? (outnx + outny) : (outnx && outny);

    assign outno = no ? (~out) : (out);

    assign zr = (outno == 16'h0000) ? 1 : 0;
    assign ng = (outno[15] == 1) ? 1 : 0;

endmodule

02/ALU_tb.v
`default_nettype none
module ALU_tb();
    
    integer file;

    reg [15:0] x, y;
    reg zx, nx, zy, ny, f, no;
    wire [15:0] out;
    wire zr, ng;

    reg [55:0] testvectors [35:0];

    ALU dut(
	    .x(x),
	    .y(y),
	    .zx(zx),
	    .nx(nx),
	    .zy(zy),
	    .ny(ny),
	    .f(f),
	    .no(no),
	    .out(out),
	    .zr(zr),
	    .ng(ng)
    );

    task display;
        #1 $fwrite(file, "| %16b | %16b | %1b | %1b | %1b | %1b | %1b | %1b | %16b | %1b | %1b |\n", x, y, zx, nx, zy, ny, f, no, out, zr, ng);
    endtask

    initial begin
        $dumpfile("ALU_tb.vcd");
        $dumpvars(0, ALU_tb);
        file = $fopen("ALU.out","w");
        $fwrite(file, "|        x         |        y         |zx |nx |zy |ny | f |no |       out        |zr |ng |\n");


        $readmemb("ALU.tv", testvectors, 0, 35);

        for(integer i = 0; i < 36; i = i + 1) begin
		x = testvectors[i][55:40];
		y = testvectors[i][39:24];
		zx = testvectors[i][23];
		nx = testvectors[i][22];
		zy = testvectors[i][21];
		ny = testvectors[i][20];
		f = testvectors[i][19];
		no = testvectors[i][18];
		display();
        end

        $finish();
    end
endmodule

02/ALU_tb.vcd
$date
	Sun Nov  3 00:22:10 2024
$end
$version
	Icarus Verilog
$end
$timescale
	1s
$end
$scope module ALU_tb $end
$var wire 1 ! zr $end
$var wire 16 " out [15:0] $end
$var wire 1 # ng $end
$var reg 1 $ f $end
$var reg 1 % no $end
$var reg 1 & nx $end
$var reg 1 ' ny $end
$var reg 16 ( x [15:0] $end
$var reg 16 ) y [15:0] $end
$var reg 1 * zx $end
$var reg 1 + zy $end
$var integer 32 , file [31:0] $end
$scope module dut $end
$var wire 1 $ f $end
$var wire 1 % no $end
$var wire 1 & nx $end
$var wire 1 ' ny $end
$var wire 16 - x [15:0] $end
$var wire 16 . y [15:0] $end
$var wire 1 * zx $end
$var wire 1 + zy $end
$var wire 1 ! zr $end
$var wire 16 / outzy [15:0] $end
$var wire 16 0 outzx [15:0] $end
$var wire 16 1 outny [15:0] $end
$var wire 16 2 outnx [15:0] $end
$var wire 16 3 outno [15:0] $end
$var wire 16 4 out [15:0] $end
$var wire 1 # ng $end
$upscope $end
$scope begin $ivl_for_loop0 $end
$var integer 32 5 i [31:0] $end
$upscope $end
$scope task display $end
$upscope $end
$upscope $end
$enddefinitions $end
$comment Show the parameter values. $end
$dumpall
$end
#0
$dumpvars
b0 5
b0 4
b0 3
b0 2
b0 1
b0 0
b0 /
b1111111111111111 .
b0 -
b10000000000000000000000000000011 ,
1+
1*
b1111111111111111 )
b0 (
0'
0&
0%
1$
0#
b0 "
1!
$end
#1
0#
0!
b1111111111111110 "
b1111111111111110 4
b1 3
b1111111111111111 1
b1111111111111111 2
1%
1'
1&
b1 5
#2
1#
b1111111111111111 "
b1111111111111111 4
b1111111111111111 3
b0 1
0%
0'
b10 5
#3
0#
1!
b0 3
b0 "
b0 4
b1111111111111111 1
b0 2
0$
1'
0&
0*
b11 5
#4
0!
b1 3
b1 "
b1 4
b1111111111111111 /
b1111111111111111 2
0'
0+
1&
1*
b100 5
#5
1#
b0 "
b0 4
b1111111111111111 3
b1111111111111111 1
b0 /
b0 2
1%
1'
1+
0&
0*
b101 5
#6
b1111111111111110 3
b1 "
b1 4
b1111111111111111 /
b1111111111111111 2
0'
0+
1&
1*
b110 5
#7
0#
1!
b0 3
b1111111111111111 "
b1111111111111111 4
b1111111111111111 1
b0 /
b0 2
1$
1'
1+
0&
0*
b111 5
#8
0!
b1 3
b1111111111111110 "
b1111111111111110 4
b1111111111111111 /
b1111111111111111 2
0'
0+
1&
1*
b1000 5
#9
0!
b1 3
b1111111111111110 "
b1111111111111110 4
b1111111111111111 1
b0 /
1'
1+
0*
b1001 5
#10
1!
b0 3
b1111111111111111 "
b1111111111111111 4
b0 1
b1111111111111111 /
0+
1*
b1010 5
#11
1#
0!
b1111111111111111 1
b1111111111111111 "
b1111111111111111 4
b1111111111111111 3
b0 /
b0 2
0%
1+
0&
0*
b1011 5
#12
b1111111111111110 3
b1111111111111110 "
b1111111111111110 4
b1111111111111111 /
b1111111111111111 2
0'
0+
1&
1*
b1100 5
#13
b1111111111111111 3
b1111111111111111 "
b1111111111111111 4
b0 2
0&
0*
b1101 5
#14
0#
0!
b1111111111111110 "
b1111111111111110 4
b1 3
b1111111111111111 2
1%
1&
b1110 5
#15
1#
b1111111111111111 3
b0 "
b0 4
b0 1
b0 2
1'
0&
b1111 5
#16
0#
1!
b0 3
b1111111111111111 1
0%
0$
0'
b10000 5
#17
1#
0!
b1111111111111111 3
b0 1
b1111111111111111 2
1%
1'
1&
b10001 5
#18
0#
1!
b0 3
b0 2
b0 /
0%
1$
0'
1+
0&
1*
b11 )
b11 .
b10001 (
b10001 -
b10010 5
#19
0#
0!
b1111111111111110 "
b1111111111111110 4
b1 3
b1111111111111111 1
b1111111111111111 2
1%
1'
1&
b10011 5
#20
1#
b1111111111111111 "
b1111111111111111 4
b1111111111111111 3
b0 1
0%
0'
b10100 5
#21
0#
0!
b1 3
b1 "
b1 4
b1111111111111111 1
b10001 2
b10001 0
0$
1'
0&
0*
b10101 5
#22
b11 1
b11 /
b1111111111111111 2
b0 0
0'
0+
1&
1*
b10110 5
#23
1#
b1111111111111110 3
b1111111111111111 1
b0 /
b10001 2
b10001 0
1%
1'
1+
0&
0*
b10111 5
#24
b11 1
b11 /
b1111111111111111 2
b0 0
0'
0+
1&
1*
b11000 5
#25
b1111111111101111 3
b10000 "
b10000 4
b1111111111111111 1
b0 /
b10001 2
b10001 0
1$
1'
1+
0&
0*
b11001 5
#26
1#
b1111111111111101 3
b10 "
b10 4
b11 1
b11 /
b1111111111111111 2
b0 0
0'
0+
1&
1*
b11010 5
#27
0#
b10010 3
b1111111111101110 2
b1111111111101101 "
b1111111111101101 4
b1111111111111111 1
b0 /
b10001 0
1'
1+
0*
b11011 5
#28
b100 3
b1111111111111011 "
b1111111111111011 4
b1111111111111100 1
b1111111111111111 2
b11 /
b0 0
0+
1*
b11100 5
#29
0#
b1111111111111111 1
b10000 "
b10000 4
b10000 3
b0 /
b10001 2
b10001 0
0%
1+
0&
0*
b11101 5
#30
0#
b10 3
b10 "
b10 4
b11 1
b11 /
b1111111111111111 2
b0 0
0'
0+
1&
1*
b11110 5
#31
b10100 3
b10100 "
b10100 4
b10001 2
b10001 0
0&
0*
b11111 5
#32
0#
b1111111111110001 "
b1111111111110001 4
b1110 3
b1111111111101110 2
1%
1&
b100000 5
#33
1#
b1111111111110010 3
b1101 "
b1101 4
b1111111111111100 1
b10001 2
1'
0&
b100001 5
#34
0#
b1 3
b1 "
b1 4
b11 1
0%
0$
0'
b100010 5
#35
1#
b1111111111111110 3
b1111111111111100 1
b1111111111101110 2
1%
1'
1&
b100011 5
#36
b100100 5
