02/HalfAdder.v
module HalfAdder(
    input a, b,
    output sum, carry);

    assign sum = a ^ b;
    assign carry = a & b;

endmodule

02/FullAdder.v
module FullAdder(
    input a, b, carry_in,
    output sum, carry_out);

    wire sum1;
    wire [1:0] carry;

    HalfAdder halfadder1(a, b, sum1, carry[0]);
    HalfAdder halfadder2(sum1, carry_in, sum, carry[1]);
    assign carry_out = carry[0] | carry[1];

endmodule

02/FullAdder_tb.v
`default_nettype none
module FullAdder_tb();
    
    integer file;

    reg a, b, carry_in;
    wire sum, carry_out;
    
    reg [4:0] testvectors [7:0];

    FullAdder dut(
	    .a(a),
	    .b(b),
	    .carry_in(carry_in),
	    .sum(sum),
	    .carry_out(carry_out)
    );

    task display;
        #1 $fwrite(file, "|   %1b   |   %1b   |   %1b   |   %1b   |   %1b   |\n", a, b, carry_in, sum, carry_out);
    endtask

    initial begin
        $dumpfile("FullAdder_tb.vcd");
        $dumpvars(0, FullAdder_tb);
        file = $fopen("FullAdder.out","w");
        $fwrite(file, "|   a   |   b   |   c   |  sum  | carry |\n");

        $readmemb("FullAdder.tv", testvectors, 0, 7);

        for(integer i = 0; i < 8; i = i + 1) begin
		a = testvectors[i][4];
		b = testvectors[i][3];
		carry_in = testvectors[i][2];
	display();
        end

        $finish();
    end
endmodule

02/FullAdder_tb.vcd
$date
	Sun Nov  3 00:17:33 2024
$end
$version
	Icarus Verilog
$end
$timescale
	1s
$end
$scope module FullAdder_tb $end
$var wire 1 ! sum $end
$var wire 1 " carry_out $end
$var reg 1 # a $end
$var reg 1 $ b $end
$var reg 1 % carry_in $end
$var integer 32 & file [31:0] $end
$scope module dut $end
$var wire 1 # a $end
$var wire 1 $ b $end
$var wire 1 % carry_in $end
$var wire 1 " carry_out $end
$var wire 1 ' sum1 $end
$var wire 1 ! sum $end
$var wire 2 ( carry [1:0] $end
$scope module halfadder1 $end
$var wire 1 # a $end
$var wire 1 $ b $end
$var wire 1 ) carry $end
$var wire 1 ' sum $end
$upscope $end
$scope module halfadder2 $end
$var wire 1 ' a $end
$var wire 1 % b $end
$var wire 1 * carry $end
$var wire 1 ! sum $end
$upscope $end
$upscope $end
$scope begin $ivl_for_loop0 $end
$var integer 32 + i [31:0] $end
$upscope $end
$scope task display $end
$upscope $end
$upscope $end
$enddefinitions $end
$comment Show the parameter values. $end
$dumpall
$end
#0
$dumpvars
b0 +
0*
0)
b0 (
0'
b10000000000000000000000000000011 &
0%
0$
0#
0"
0!
$end
#1
1!
1%
b1 +
#2
1'
0%
1$
b10 +
#3
1"
0!
b10 (
1*
1%
b11 +
#4
0"
1!
b0 (
0*
0%
0$
1#
b100 +
#5
1"
0!
b10 (
1*
1%
b101 +
#6
0*
0'
b1 (
1)
0%
1$
b110 +
#7
1!
1%
b111 +
#8
b1000 +
